qixuema/__init__.py
qixuema/config.py
qixuema/geo_utils.py
qixuema/helpers.py
qixuema/img_utils.py
qixuema/io_utils.py
qixuema/line_utils.py
qixuema/load_ckpt.py
qixuema/log_utils.py
qixuema/marker_utils.py
qixuema/np_utils.py
qixuema/o3d_utils.py
qixuema/plot_utils.py
qixuema/scipy_utils.py
qixuema/tensor_typing.py
qixuema/torch_utils.py
qixuema/trimesh_utils.py
qixuema/utils.py
qixuema/vis_samples.py
qixuema/vis_utils.py
qixuema-0.0.9.dist-info/METADATA
qixuema-0.0.9.dist-info/WHEEL
qixuema-0.0.9.dist-info/licenses/LICENSE
qixuema-0.0.9.dist-info/RECORD
