Metadata-Version: 2.4
Name: qixuema
Version: 0.0.9
Summary: Shared utilities
Author-email: Xueqi Ma <qixuemaa@gmail.com>
License-File: LICENSE
Requires-Python: >=3.11
Requires-Dist: deprecated>=1.2.14
Requires-Dist: einops>=0.8.0
Requires-Dist: einx>=0.3.0
Requires-Dist: numpy
Requires-Dist: packaging>=21.0
Requires-Dist: pyyaml>=6.0.1
Provides-Extra: dev
Requires-Dist: build; extra == 'dev'
Requires-Dist: pytest; extra == 'dev'
Requires-Dist: ruff; extra == 'dev'
